{"zmk":{"nested":{"studio":{"nested":{"Request":{"oneofs":{"subsystem":{"oneof":["core","behaviors","keymap","pointing","combo","macros"]}},"fields":{"requestId":{"type":"uint32","id":1},"core":{"type":"zmk.core.Request","id":3},"behaviors":{"type":"zmk.behaviors.Request","id":4},"keymap":{"type":"zmk.keymap.Request","id":5},"pointing":{"type":"zmk.pointing.Request","id":6},"combo":{"type":"zmk.combo.Request","id":7},"macros":{"type":"zmk.macros.Request","id":8}}},"Response":{"oneofs":{"type":{"oneof":["requestResponse","notification"]}},"fields":{"requestResponse":{"type":"RequestResponse","id":1},"notification":{"type":"Notification","id":2}}},"RequestResponse":{"oneofs":{"subsystem":{"oneof":["meta","core","behaviors","keymap","pointing","combo","macros"]}},"fields":{"requestId":{"type":"uint32","id":1},"meta":{"type":"zmk.meta.Response","id":2},"core":{"type":"zmk.core.Response","id":3},"behaviors":{"type":"zmk.behaviors.Response","id":4},"keymap":{"type":"zmk.keymap.Response","id":5},"pointing":{"type":"zmk.pointing.Response","id":6},"combo":{"type":"zmk.combo.Response","id":7},"macros":{"type":"zmk.macros.Response","id":8}}},"Notification":{"oneofs":{"subsystem":{"oneof":["core","keymap","pointing"]}},"fields":{"core":{"type":"zmk.core.Notification","id":2},"keymap":{"type":"zmk.keymap.Notification","id":5},"pointing":{"type":"zmk.pointing.Notification","id":6}}}}},"meta":{"nested":{"ErrorConditions":{"values":{"GENERIC":0,"UNLOCK_REQUIRED":1,"RPC_NOT_FOUND":2,"MSG_DECODE_FAILED":3,"MSG_ENCODE_FAILED":4}},"Response":{"oneofs":{"responseType":{"oneof":["noResponse","simpleError"]}},"fields":{"noResponse":{"type":"bool","id":1},"simpleError":{"type":"ErrorConditions","id":2}}}}},"core":{"nested":{"LockState":{"values":{"ZMK_STUDIO_CORE_LOCK_STATE_LOCKED":0,"ZMK_STUDIO_CORE_LOCK_STATE_UNLOCKED":1}},"Request":{"oneofs":{"requestType":{"oneof":["getDeviceInfo","getLockState","lock","resetSettings","getBleProfiles","getTappingTerm","setTappingTerm","setBleProfileName"]}},"fields":{"getDeviceInfo":{"type":"bool","id":1},"getLockState":{"type":"bool","id":2},"lock":{"type":"bool","id":3},"resetSettings":{"type":"bool","id":4},"getBleProfiles":{"type":"bool","id":5},"getTappingTerm":{"type":"bool","id":6},"setTappingTerm":{"type":"SetTappingTermRequest","id":7},"setBleProfileName":{"type":"SetBleProfileNameRequest","id":8}}},"Response":{"oneofs":{"responseType":{"oneof":["getDeviceInfo","getLockState","resetSettings","getBleProfiles","getTappingTerm","setTappingTerm","setBleProfileName"]}},"fields":{"getDeviceInfo":{"type":"GetDeviceInfoResponse","id":1},"getLockState":{"type":"LockState","id":2},"resetSettings":{"type":"bool","id":4},"getBleProfiles":{"type":"GetBleProfilesResponse","id":5},"getTappingTerm":{"type":"GetTappingTermResponse","id":6},"setTappingTerm":{"type":"bool","id":7},"setBleProfileName":{"type":"bool","id":8}}},"GetDeviceInfoResponse":{"fields":{"name":{"type":"string","id":1},"serialNumber":{"type":"bytes","id":2},"firmwareVersion":{"type":"string","id":3}}},"BleProfileInfo":{"fields":{"name":{"type":"string","id":1},"connected":{"type":"bool","id":2}}},"GetBleProfilesResponse":{"fields":{"profiles":{"rule":"repeated","type":"BleProfileInfo","id":1},"activeIndex":{"type":"uint32","id":2}}},"SetTappingTermRequest":{"fields":{"tappingTermMs":{"type":"uint32","id":1}}},"SetBleProfileNameRequest":{"fields":{"profileIndex":{"type":"uint32","id":1},"name":{"type":"string","id":2}}},"GetTappingTermResponse":{"fields":{"tappingTermMs":{"type":"uint32","id":1},"defaultTappingTermMs":{"type":"uint32","id":2}}},"Notification":{"oneofs":{"notificationType":{"oneof":["lockStateChanged"]}},"fields":{"lockStateChanged":{"type":"LockState","id":1}}}}},"behaviors":{"nested":{"Request":{"oneofs":{"requestType":{"oneof":["listAllBehaviors","getBehaviorDetails"]}},"fields":{"listAllBehaviors":{"type":"bool","id":1},"getBehaviorDetails":{"type":"GetBehaviorDetailsRequest","id":2}}},"GetBehaviorDetailsRequest":{"fields":{"behaviorId":{"type":"uint32","id":1}}},"Response":{"oneofs":{"responseType":{"oneof":["listAllBehaviors","getBehaviorDetails"]}},"fields":{"listAllBehaviors":{"type":"ListAllBehaviorsResponse","id":1},"getBehaviorDetails":{"type":"GetBehaviorDetailsResponse","id":2}}},"ListAllBehaviorsResponse":{"fields":{"behaviors":{"rule":"repeated","type":"uint32","id":1}}},"GetBehaviorDetailsResponse":{"fields":{"id":{"type":"uint32","id":1},"displayName":{"type":"string","id":2},"metadata":{"rule":"repeated","type":"BehaviorBindingParametersSet","id":3}}},"BehaviorBindingParametersSet":{"fields":{"param1":{"rule":"repeated","type":"BehaviorParameterValueDescription","id":1},"param2":{"rule":"repeated","type":"BehaviorParameterValueDescription","id":2}}},"BehaviorParameterValueDescriptionRange":{"fields":{"min":{"type":"int32","id":1},"max":{"type":"int32","id":2}}},"BehaviorParameterNil":{"fields":{}},"BehaviorParameterLayerId":{"fields":{}},"BehaviorParameterHidUsage":{"fields":{"keyboardMax":{"type":"uint32","id":1},"consumerMax":{"type":"uint32","id":2}}},"BehaviorParameterValueDescription":{"oneofs":{"valueType":{"oneof":["nil","constant","range","hidUsage","layerId"]}},"fields":{"name":{"type":"string","id":1},"nil":{"type":"BehaviorParameterNil","id":2},"constant":{"type":"uint32","id":3},"range":{"type":"BehaviorParameterValueDescriptionRange","id":4},"hidUsage":{"type":"BehaviorParameterHidUsage","id":5},"layerId":{"type":"BehaviorParameterLayerId","id":6}}}}},"keymap":{"nested":{"Request":{"oneofs":{"requestType":{"oneof":["getKeymap","setLayerBinding","checkUnsavedChanges","saveChanges","discardChanges","getPhysicalLayouts","setActivePhysicalLayout","moveLayer","addLayer","removeLayer","restoreLayer","setLayerProps"]}},"fields":{"getKeymap":{"type":"bool","id":1},"setLayerBinding":{"type":"SetLayerBindingRequest","id":2},"checkUnsavedChanges":{"type":"bool","id":3},"saveChanges":{"type":"bool","id":4},"discardChanges":{"type":"bool","id":5},"getPhysicalLayouts":{"type":"bool","id":6},"setActivePhysicalLayout":{"type":"uint32","id":7},"moveLayer":{"type":"MoveLayerRequest","id":8},"addLayer":{"type":"AddLayerRequest","id":9},"removeLayer":{"type":"RemoveLayerRequest","id":10},"restoreLayer":{"type":"RestoreLayerRequest","id":11},"setLayerProps":{"type":"SetLayerPropsRequest","id":12}}},"Response":{"oneofs":{"responseType":{"oneof":["getKeymap","setLayerBinding","checkUnsavedChanges","saveChanges","discardChanges","getPhysicalLayouts","setActivePhysicalLayout","moveLayer","addLayer","removeLayer","restoreLayer","setLayerProps"]}},"fields":{"getKeymap":{"type":"Keymap","id":1},"setLayerBinding":{"type":"SetLayerBindingResponse","id":2},"checkUnsavedChanges":{"type":"bool","id":3},"saveChanges":{"type":"SaveChangesResponse","id":4},"discardChanges":{"type":"bool","id":5},"getPhysicalLayouts":{"type":"PhysicalLayouts","id":6},"setActivePhysicalLayout":{"type":"SetActivePhysicalLayoutResponse","id":7},"moveLayer":{"type":"MoveLayerResponse","id":8},"addLayer":{"type":"AddLayerResponse","id":9},"removeLayer":{"type":"RemoveLayerResponse","id":10},"restoreLayer":{"type":"RestoreLayerResponse","id":11},"setLayerProps":{"type":"SetLayerPropsResponse","id":12}}},"Notification":{"oneofs":{"notificationType":{"oneof":["unsavedChangesStatusChanged"]}},"fields":{"unsavedChangesStatusChanged":{"type":"bool","id":1}}},"SaveChangesResponse":{"oneofs":{"result":{"oneof":["ok","err"]}},"fields":{"ok":{"type":"bool","id":1},"err":{"type":"SaveChangesErrorCode","id":2}}},"SaveChangesErrorCode":{"values":{"SAVE_CHANGES_ERR_OK":0,"SAVE_CHANGES_ERR_GENERIC":1,"SAVE_CHANGES_ERR_NOT_SUPPORTED":2,"SAVE_CHANGES_ERR_NO_SPACE":3}},"SetLayerBindingResponse":{"values":{"SET_LAYER_BINDING_RESP_OK":0,"SET_LAYER_BINDING_RESP_INVALID_LOCATION":1,"SET_LAYER_BINDING_RESP_INVALID_BEHAVIOR":2,"SET_LAYER_BINDING_RESP_INVALID_PARAMETERS":3}},"SetActivePhysicalLayoutResponse":{"oneofs":{"result":{"oneof":["ok","err"]}},"fields":{"ok":{"type":"Keymap","id":1},"err":{"type":"SetActivePhysicalLayoutErrorCode","id":2}}},"MoveLayerErrorCode":{"values":{"MOVE_LAYER_ERR_OK":0,"MOVE_LAYER_ERR_GENERIC":1,"MOVE_LAYER_ERR_INVALID_LAYER":2,"MOVE_LAYER_ERR_INVALID_DESTINATION":3}},"MoveLayerResponse":{"oneofs":{"result":{"oneof":["ok","err"]}},"fields":{"ok":{"type":"Keymap","id":1},"err":{"type":"MoveLayerErrorCode","id":2}}},"AddLayerResponse":{"oneofs":{"result":{"oneof":["ok","err"]}},"fields":{"ok":{"type":"AddLayerResponseDetails","id":1},"err":{"type":"AddLayerErrorCode","id":2}}},"AddLayerErrorCode":{"values":{"ADD_LAYER_ERR_OK":0,"ADD_LAYER_ERR_GENERIC":1,"ADD_LAYER_ERR_NO_SPACE":2}},"AddLayerResponseDetails":{"fields":{"index":{"type":"uint32","id":1},"layer":{"type":"Layer","id":2}}},"RemoveLayerResponse":{"oneofs":{"result":{"oneof":["ok","err"]}},"fields":{"ok":{"type":"RemoveLayerOk","id":1},"err":{"type":"RemoveLayerErrorCode","id":2}}},"RemoveLayerOk":{"fields":{}},"RemoveLayerErrorCode":{"values":{"REMOVE_LAYER_ERR_OK":0,"REMOVE_LAYER_ERR_GENERIC":1,"REMOVE_LAYER_ERR_INVALID_INDEX":2}},"RestoreLayerResponse":{"oneofs":{"result":{"oneof":["ok","err"]}},"fields":{"ok":{"type":"Layer","id":1},"err":{"type":"RestoreLayerErrorCode","id":2}}},"RestoreLayerErrorCode":{"values":{"RESTORE_LAYER_ERR_OK":0,"RESTORE_LAYER_ERR_GENERIC":1,"RESTORE_LAYER_ERR_INVALID_ID":2,"RESTORE_LAYER_ERR_INVALID_INDEX":3}},"SetLayerPropsResponse":{"values":{"SET_LAYER_PROPS_RESP_OK":0,"SET_LAYER_PROPS_RESP_ERR_GENERIC":1,"SET_LAYER_PROPS_RESP_ERR_INVALID_ID":2}},"SetActivePhysicalLayoutErrorCode":{"values":{"SET_ACTIVE_PHYSICAL_LAYOUT_ERR_OK":0,"SET_ACTIVE_PHYSICAL_LAYOUT_ERR_GENERIC":1,"SET_ACTIVE_PHYSICAL_LAYOUT_ERR_INVALID_LAYOUT_INDEX":2}},"SetLayerBindingRequest":{"fields":{"layerId":{"type":"uint32","id":1},"keyPosition":{"type":"int32","id":2},"binding":{"type":"BehaviorBinding","id":3}}},"MoveLayerRequest":{"fields":{"startIndex":{"type":"uint32","id":1},"destIndex":{"type":"uint32","id":2}}},"AddLayerRequest":{"fields":{}},"RemoveLayerRequest":{"fields":{"layerIndex":{"type":"uint32","id":1}}},"RestoreLayerRequest":{"fields":{"layerId":{"type":"uint32","id":1},"atIndex":{"type":"uint32","id":2}}},"SetLayerPropsRequest":{"fields":{"layerId":{"type":"uint32","id":1},"name":{"type":"string","id":2},"color":{"type":"uint32","id":3}}},"Keymap":{"fields":{"layers":{"rule":"repeated","type":"Layer","id":1},"availableLayers":{"type":"uint32","id":2},"maxLayerNameLength":{"type":"uint32","id":3}}},"Layer":{"fields":{"id":{"type":"uint32","id":1},"name":{"type":"string","id":2},"bindings":{"rule":"repeated","type":"BehaviorBinding","id":3},"color":{"type":"uint32","id":4}}},"BehaviorBinding":{"fields":{"behaviorId":{"type":"sint32","id":1},"param1":{"type":"uint32","id":2},"param2":{"type":"uint32","id":3}}},"PhysicalLayouts":{"fields":{"activeLayoutIndex":{"type":"uint32","id":1},"layouts":{"rule":"repeated","type":"PhysicalLayout","id":2}}},"PhysicalLayout":{"fields":{"name":{"type":"string","id":1},"keys":{"rule":"repeated","type":"KeyPhysicalAttrs","id":2}}},"KeyPhysicalAttrs":{"fields":{"width":{"type":"sint32","id":1},"height":{"type":"sint32","id":2},"x":{"type":"sint32","id":3},"y":{"type":"sint32","id":4},"r":{"type":"sint32","id":5},"rx":{"type":"sint32","id":6},"ry":{"type":"sint32","id":7}}}}},"pointing":{"nested":{"SensitivityScale":{"fields":{"numerator":{"type":"sint32","id":1},"denominator":{"type":"uint32","id":2}}},"SetSensitivityRequest":{"fields":{"cursor":{"type":"SensitivityScale","id":1},"scroll":{"type":"SensitivityScale","id":2},"cpi":{"type":"uint32","id":3}}},"SetSensitivityErrorCode":{"values":{"SET_SENSITIVITY_ERR_OK":0,"SET_SENSITIVITY_ERR_UNSUPPORTED":1,"SET_SENSITIVITY_ERR_INVALID":2,"SET_SENSITIVITY_ERR_STORAGE":3}},"SetSensitivityResponse":{"oneofs":{"result":{"oneof":["ok","err"]}},"fields":{"ok":{"type":"bool","id":1},"err":{"type":"SetSensitivityErrorCode","id":2}}},"GetSensitivityRequest":{"fields":{}},"GetSensitivityResponse":{"fields":{"cursor":{"type":"SensitivityScale","id":1},"scroll":{"type":"SensitivityScale","id":2},"cpi":{"type":"uint32","id":3}}},"GetAutoLayerRequest":{"fields":{}},"GetAutoLayerResponse":{"fields":{"enabled":{"type":"bool","id":1},"requirePriorIdleMs":{"type":"uint32","id":2},"excludedPositions":{"rule":"repeated","type":"uint32","id":3},"motionThreshold":{"type":"uint32","id":4}}},"SetAutoLayerErrorCode":{"values":{"SET_AUTO_LAYER_ERR_OK":0,"SET_AUTO_LAYER_ERR_UNSUPPORTED":1,"SET_AUTO_LAYER_ERR_INVALID":2,"SET_AUTO_LAYER_ERR_STORAGE":3}},"SetAutoLayerRequest":{"fields":{"enabled":{"type":"bool","id":1},"requirePriorIdleMs":{"type":"uint32","id":2},"excludedPositions":{"rule":"repeated","type":"uint32","id":3},"motionThreshold":{"type":"uint32","id":4}}},"SetAutoLayerResponse":{"oneofs":{"result":{"oneof":["ok","err"]}},"fields":{"ok":{"type":"bool","id":1},"err":{"type":"SetAutoLayerErrorCode","id":2}}},"Request":{"oneofs":{"requestType":{"oneof":["setSensitivity","getSensitivity","getAutoLayer","setAutoLayer","setPrecisionScale","getPrecisionScale","setAccel","getAccel"]}},"fields":{"setSensitivity":{"type":"SetSensitivityRequest","id":1},"getSensitivity":{"type":"GetSensitivityRequest","id":2},"getAutoLayer":{"type":"GetAutoLayerRequest","id":3},"setAutoLayer":{"type":"SetAutoLayerRequest","id":4},"setPrecisionScale":{"type":"SetPrecisionScaleRequest","id":5},"getPrecisionScale":{"type":"GetPrecisionScaleRequest","id":6},"setAccel":{"type":"SetAccelRequest","id":7},"getAccel":{"type":"GetAccelRequest","id":8}}},"Response":{"oneofs":{"responseType":{"oneof":["setSensitivity","getSensitivity","getAutoLayer","setAutoLayer","setPrecisionScale","getPrecisionScale","setAccel","getAccel"]}},"fields":{"setSensitivity":{"type":"SetSensitivityResponse","id":1},"getSensitivity":{"type":"GetSensitivityResponse","id":2},"getAutoLayer":{"type":"GetAutoLayerResponse","id":3},"setAutoLayer":{"type":"SetAutoLayerResponse","id":4},"setPrecisionScale":{"type":"SetPrecisionScaleResponse","id":5},"getPrecisionScale":{"type":"GetPrecisionScaleResponse","id":6},"setAccel":{"type":"SetAccelResponse","id":7},"getAccel":{"type":"GetAccelResponse","id":8}}},"Notification":{"fields":{}},"SetPrecisionScaleRequest":{"fields":{"precision":{"type":"SensitivityScale","id":1}}},"SetPrecisionScaleErrorCode":{"values":{"SET_PRECISION_SCALE_ERR_OK":0,"SET_PRECISION_SCALE_ERR_INVALID":1,"SET_PRECISION_SCALE_ERR_STORAGE":2}},"SetPrecisionScaleResponse":{"oneofs":{"result":{"oneof":["ok","err"]}},"fields":{"ok":{"type":"bool","id":1},"err":{"type":"SetPrecisionScaleErrorCode","id":2}}},"GetPrecisionScaleRequest":{"fields":{}},"GetPrecisionScaleResponse":{"fields":{"precision":{"type":"SensitivityScale","id":1}}},"AccelConfig":{"fields":{"enabled":{"type":"bool","id":1},"maxMilli":{"type":"uint32","id":2},"threshold":{"type":"uint32","id":3},"range":{"type":"uint32","id":4}}},"SetAccelRequest":{"fields":{"accel":{"type":"AccelConfig","id":1}}},"SetAccelResponse":{"oneofs":{"result":{"oneof":["ok","err"]}},"fields":{"ok":{"type":"bool","id":1},"err":{"type":"SetSensitivityErrorCode","id":2}}},"GetAccelRequest":{"fields":{}},"GetAccelResponse":{"fields":{"accel":{"type":"AccelConfig","id":1}}}}},"combo":{"nested":{"Request":{"oneofs":{"request_type":{"oneof":["get_combos","set_combo","add_combo","remove_combo"]}},"fields":{"get_combos":{"type":"bool","id":1},"set_combo":{"type":"SetComboRequest","id":2},"add_combo":{"type":"AddComboRequest","id":3},"remove_combo":{"type":"RemoveComboRequest","id":4}}},"Response":{"oneofs":{"response_type":{"oneof":["get_combos","set_combo","add_combo","remove_combo"]}},"fields":{"get_combos":{"type":"CombosResponse","id":1},"set_combo":{"type":"SetComboResponse","id":2},"add_combo":{"type":"AddComboResponse","id":3},"remove_combo":{"type":"RemoveComboResponse","id":4}}},"ComboConfig":{"fields":{"keyPositions":{"rule":"repeated","type":"uint32","id":1},"binding":{"type":"zmk.keymap.BehaviorBinding","id":2},"timeoutMs":{"type":"uint32","id":3},"requirePriorIdleMs":{"type":"uint32","id":4},"layerMask":{"type":"uint32","id":5},"slowRelease":{"type":"bool","id":6}}},"CombosResponse":{"fields":{"combos":{"rule":"repeated","type":"ComboConfig","id":1},"maxCombos":{"type":"uint32","id":2}}},"SetComboRequest":{"fields":{"index":{"type":"uint32","id":1},"combo":{"type":"ComboConfig","id":2}}},"SetComboResponse":{"values":{"SET_COMBO_RESP_OK":0,"SET_COMBO_RESP_ERR_GENERIC":1,"SET_COMBO_RESP_ERR_INVALID_INDEX":2,"SET_COMBO_RESP_ERR_INVALID_PARAMS":3}},"AddComboRequest":{"fields":{"combo":{"type":"ComboConfig","id":1}}},"AddComboResponse":{"oneofs":{"result":{"oneof":["ok","err"]}},"fields":{"ok":{"type":"uint32","id":1},"err":{"type":"AddComboErrorCode","id":2}}},"AddComboErrorCode":{"values":{"ADD_COMBO_ERR_OK":0,"ADD_COMBO_ERR_GENERIC":1,"ADD_COMBO_ERR_NO_SPACE":2,"ADD_COMBO_ERR_INVALID_PARAMS":3}},"RemoveComboRequest":{"fields":{"index":{"type":"uint32","id":1}}},"RemoveComboResponse":{"values":{"REMOVE_COMBO_RESP_OK":0,"REMOVE_COMBO_RESP_ERR_GENERIC":1,"REMOVE_COMBO_RESP_ERR_INVALID_INDEX":2}}}},"macros":{"nested":{"Request":{"oneofs":{"requestType":{"oneof":["listAllMacros","getMacroData","setMacro"]}},"fields":{"listAllMacros":{"type":"bool","id":1},"getMacroData":{"type":"GetMacroDataRequest","id":2},"setMacro":{"type":"SetMacroRequest","id":3}}},"Response":{"oneofs":{"responseType":{"oneof":["listAllMacros","getMacroData","setMacro"]}},"fields":{"listAllMacros":{"type":"ListAllMacrosResponse","id":1},"getMacroData":{"type":"GetMacroDataResponse","id":2},"setMacro":{"type":"SetMacroResponse","id":3}}},"MacroStep":{"fields":{"actionType":{"type":"uint32","id":1},"value":{"type":"uint32","id":2}}},"MacroSequence":{"fields":{"id":{"type":"uint32","id":1},"name":{"type":"string","id":2},"steps":{"rule":"repeated","type":"MacroStep","id":3}}},"ListAllMacrosResponse":{"fields":{"macros":{"rule":"repeated","type":"MacroSummary","id":1},"maxMacros":{"type":"uint32","id":2}}},"MacroSummary":{"fields":{"id":{"type":"uint32","id":1},"name":{"type":"string","id":2},"stepCount":{"type":"uint32","id":3}}},"GetMacroDataRequest":{"fields":{"macroId":{"type":"uint32","id":1}}},"GetMacroDataResponse":{"oneofs":{"result":{"oneof":["macro","err"]}},"fields":{"macro":{"type":"MacroSequence","id":1},"err":{"type":"GetMacroDataErrorCode","id":2}}},"GetMacroDataErrorCode":{"values":{"GET_MACRO_DATA_ERR_OK":0,"GET_MACRO_DATA_ERR_GENERIC":1,"GET_MACRO_DATA_ERR_INVALID_ID":2}},"SetMacroRequest":{"fields":{"macro":{"type":"MacroSequence","id":1}}},"SetMacroResponse":{"values":{"SET_MACRO_RESP_OK":0,"SET_MACRO_RESP_ERR_GENERIC":1,"SET_MACRO_RESP_ERR_INVALID_ID":2,"SET_MACRO_RESP_ERR_TOO_MANY_STEPS":3,"SET_MACRO_RESP_ERR_NO_SPACE":4}}}}}}}